{
  "type": "FeatureCollection",
  "name": "burke_lake_parking",
  "features": [
    {
      "type": "Feature",
      "properties": {
        "parking_id": 1,
        "name": "Main Entrance Lot",
        "capacity": 180,
        "accessible_spaces": 8,
        "hours": "Park hours"
      },
      "geometry": {
        "type": "Point",
        "coordinates": [
          -77.3202,
          38.761
        ]
      }
    },
    {
      "type": "Feature",
      "properties": {
        "parking_id": 2,
        "name": "Marina Lot",
        "capacity": 75,
        "accessible_spaces": 4,
        "hours": "Park hours"
      },
      "geometry": {
        "type": "Point",
        "coordinates": [
          -77.3197,
          38.7626
        ]
      }
    },
    {
      "type": "Feature",
      "properties": {
        "parking_id": 3,
        "name": "South Picnic Lot",
        "capacity": 60,
        "accessible_spaces": 3,
        "hours": "Park hours"
      },
      "geometry": {
        "type": "Point",
        "coordinates": [
          -77.315,
          38.7583
        ]
      }
    }
  ]
}